cannlytics/__init__.py
cannlytics/cannlytics.py
cannlytics/ai/__init__.py
cannlytics/ai/ai.py
cannlytics/auth/__init__.py
cannlytics/auth/auth.py
cannlytics/data/__init__.py
cannlytics/data/data.py
cannlytics/data/tools.py
cannlytics/data/ccrs/__init__.py
cannlytics/data/ccrs/ccrs.py
cannlytics/data/ccrs/constants.py
cannlytics/data/coas/__init__.py
cannlytics/data/coas/coa_ai.py
cannlytics/data/coas/coas.py
cannlytics/data/coas/algorithms/__init__.py
cannlytics/data/coas/algorithms/acs.py
cannlytics/data/coas/algorithms/anresco.py
cannlytics/data/coas/algorithms/cannalysis.py
cannlytics/data/coas/algorithms/cannasafe.py
cannlytics/data/coas/algorithms/cdx.py
cannlytics/data/coas/algorithms/confidence.py
cannlytics/data/coas/algorithms/confidentcannabis.py
cannlytics/data/coas/algorithms/green_scientific.py
cannlytics/data/coas/algorithms/greenleaflab.py
cannlytics/data/coas/algorithms/kaycha.py
cannlytics/data/coas/algorithms/kcalabs.py
cannlytics/data/coas/algorithms/mcrlabs.py
cannlytics/data/coas/algorithms/moderncanna.py
cannlytics/data/coas/algorithms/mtl.py
cannlytics/data/coas/algorithms/sclabs.py
cannlytics/data/coas/algorithms/sonoma.py
cannlytics/data/coas/algorithms/steephill.py
cannlytics/data/coas/algorithms/tagleaf.py
cannlytics/data/coas/algorithms/terplife.py
cannlytics/data/coas/algorithms/veda.py
cannlytics/data/gis/__init__.py
cannlytics/data/gis/gis.py
cannlytics/data/market/__init__.py
cannlytics/data/market/market.py
cannlytics/data/opendata/__init__.py
cannlytics/data/opendata/opendata.py
cannlytics/data/sales/__init__.py
cannlytics/data/sales/labels.py
cannlytics/data/sales/receipts_ai.py
cannlytics/data/strains/__init__.py
cannlytics/data/strains/patents.py
cannlytics/data/strains/strains_ai.py
cannlytics/data/web/__init__.py
cannlytics/data/web/web.py
cannlytics/firebase/__init__.py
cannlytics/firebase/firebase.py
cannlytics/lims/__init__.py
cannlytics/lims/calculations.py
cannlytics/lims/certificates.py
cannlytics/lims/instruments.py
cannlytics-0.0.17.dist-info/LICENSE
cannlytics-0.0.17.dist-info/METADATA
cannlytics-0.0.17.dist-info/WHEEL
cannlytics-0.0.17.dist-info/top_level.txt
cannlytics-0.0.17.dist-info/RECORD
