Metadata-Version: 2.1
Name: cannlytics
Version: 0.0.17
Summary: 🔥 Cannlytics is a suite of tools that you can use to wrangle, standardize, and analyze cannabis data
Home-page: https://github.com/cannlytics/cannlytics
Author: Cannlytics
Author-email: dev@cannlytics.com
License: MIT
Keywords: cannlytics
Classifier: Intended Audience :: Developers
Classifier: License :: OSI Approved :: MIT License
Classifier: Natural Language :: English
Classifier: Programming Language :: Python :: 3.9
Requires-Python: >=3.9
License-File: LICENSE
Requires-Dist: beautifulsoup4
Requires-Dist: firebase-admin
Requires-Dist: fredapi
Requires-Dist: google-cloud-secret-manager
Requires-Dist: google-cloud-firestore
Requires-Dist: googlemaps
Requires-Dist: matplotlib
Requires-Dist: numpy
Requires-Dist: openai
Requires-Dist: openpyxl
Requires-Dist: opencv-python
Requires-Dist: pandas
Requires-Dist: pdfplumber
Requires-Dist: Pillow
Requires-Dist: pyarrow
Requires-Dist: pydantic
Requires-Dist: pypdf
Requires-Dist: pytesseract
Requires-Dist: python-dateutil
Requires-Dist: python-dotenv
Requires-Dist: pyzbar
Requires-Dist: scikit-learn
Requires-Dist: selenium
Requires-Dist: statsmodels
Requires-Dist: Wand
Requires-Dist: ulid-py
Requires-Dist: xxhash
Requires-Dist: zipcodes
Provides-Extra: dev
Requires-Dist: ocean-lib ; extra == 'dev'
Requires-Dist: xlwings ; extra == 'dev'
Provides-Extra: test
